Workbook
Name anos: Simulador!$D$16
Name patimonio: Simulador!$D$18
Name rendimento_carteira: Simulador!$D$11
Name salario: Simulador!$D$10
Name sugestao_investimento: Simulador!$D$12
Name taxa_mensal: Simulador!$D$17

Sheet Perguntas
A1: Criar um simulador simples de investimentos
A2: Quanto investir or mês
A3: Por quantos anos tenho que investir
A4: Deve ter taxa de redimento mensal
A5: Qual patrimonio total terei
A6: Quanto é os dividendo mensais

Sheet Simulador
B9: CONFIGURAÇÕES
B10: Salário | D10: 4200
B11: Rendimento Carteira | D11: 0.006
B12: Sugestão de Investimento | D12: =D10*30% -> 1260
B14: INVENTIMENTO MENSAL
B15: Quanto investir por mês? | D15: 1260
B16: Por quantos anos? | D16: 10
B17: Taxa de rendimento mensal? | D17: 0.01079
B18: Patrimonio acumulado? | D18: =FV(taxa_mensal,anos*12,D15*-1) -> 306538.11
B19: Dividendos mensais? | D19: =patimonio*taxa_mensal -> 3307.5462
A21: 2 | B21: CENÁRIOS | D21: RENDIMENTO
A22: 5 | B22: Quanto em 2 anos? | C22: =FV($D$17,$A21*12,$D$15*-1) -> 34306.81 | D22: =C22*rendimento_carteira -> 205.84086
A23: 10 | B23: Quanto em 5 anos? | C23: =FV($D$17,$A22*12,$D$15*-1) -> 105558.91 | D23: =C23*rendimento_carteira -> 633.35347
A24: 20 | B24: Quanto em 10 anos? | C24: =FV($D$17,$A23*12,$D$15*-1) -> 306538.11 | D24: =C24*rendimento_carteira -> 1839.2286
A25: 30 | B25: Quanto em 20 anos? | C25: =FV($D$17,$A24*12,$D$15*-1) -> 1417750 | D25: =C25*rendimento_carteira -> 8506.4999
B26: Quanto em 30 anos? | C26: =FV($D$17,$A25*12,$D$15*-1) -> 5445933.8 | D26: =C26*rendimento_carteira -> 32675.603
B29: PERFIL | C29: Conservador
B30: VALOR A SER INVESTIDO POR MÊS | C30: =D15 -> 1260
B33: TIPO DE FII | C33: Percentual Sugerido | D33: Valores
B34: PAPEL | C34: =VLOOKUP($C$29&"-"&B34,Apoio!A:D,4,0) -> 0.3 | D34: =C34*$C$30 -> 378
B35: TIJOLO | C35: =VLOOKUP($C$29&"-"&B35,Apoio!A:D,4,0) -> 0.5 | D35: =C35*$C$30 -> 630
B36: HIBRIDOS | C36: =VLOOKUP($C$29&"-"&B36,Apoio!A:D,4,0) -> 0.1 | D36: =C36*$C$30 -> 126
B37: FOFs | C37: =VLOOKUP($C$29&"-"&B37,Apoio!A:D,4,0) -> 0.1 | D37: =C37*$C$30 -> 126
B38: DESENVOLVIMENTO | C38: =VLOOKUP($C$29&"-"&B38,Apoio!A:D,4,0) -> 0 | D38: =C38*$C$30 -> 0
B39: HOTELARIAS | C39: =VLOOKUP($C$29&"-"&B39,Apoio!A:D,4,0) -> 0 | D39: =C39*$C$30 -> 0
D40: =SUM(D34:D39) -> 1260

Sheet Apoio
A2: CHAVE | B2: PERFIL | C2: TIPO DE FII | D2: %
A3: =B3&"-"&C3 -> Conservador-PAPEL | B3: Conservador | C3: PAPEL | D3: 0.3
A4: =B4&"-"&C4 -> Conservador-TIJOLO | B4: Conservador | C4: TIJOLO | D4: 0.5
A5: =B5&"-"&C5 -> Conservador-HIBRIDOS | B5: Conservador | C5: HIBRIDOS | D5: 0.1
A6: =B6&"-"&C6 -> Conservador-FOFs | B6: Conservador | C6: FOFs | D6: 0.1
A7: =B7&"-"&C7 -> Conservador-DESENVOLVIMENTO | B7: Conservador | C7: DESENVOLVIMENTO | D7: 0
A8: =B8&"-"&C8 -> Conservador-HOTELARIAS | B8: Conservador | C8: HOTELARIAS | D8: 0
A9: =B9&"-"&C9 -> Moderado-PAPEL | B9: Moderado | C9: PAPEL | D9: 0.32
A10: =B10&"-"&C10 -> Moderado-TIJOLO | B10: Moderado | C10: TIJOLO | D10: 0.4
A11: =B11&"-"&C11 -> Moderado-HIBRIDOS | B11: Moderado | C11: HIBRIDOS | D11: 0.1
A12: =B12&"-"&C12 -> Moderado-FOFs | B12: Moderado | C12: FOFs | D12: 0.08
A13: =B13&"-"&C13 -> Moderado-DESENVOLVIMENTO | B13: Moderado | C13: DESENVOLVIMENTO | D13: 0.05
A14: =B14&"-"&C14 -> Moderado-HOTELARIAS | B14: Moderado | C14: HOTELARIAS | D14: 0.05
... A20: =B20&"-"&C20 -> Agressivo-HOTELARIAS | B20: Agressivo | C20: HOTELARIAS | D20: 0.1
